LICENSE.txt
README.md
setup.cfg
setup.py
fastapi_ecommerce_ext.egg-info/PKG-INFO
fastapi_ecommerce_ext.egg-info/SOURCES.txt
fastapi_ecommerce_ext.egg-info/dependency_links.txt
fastapi_ecommerce_ext.egg-info/requires.txt
fastapi_ecommerce_ext.egg-info/top_level.txt
fastapi_ecommerce_ext/logger/__init__.py
fastapi_ecommerce_ext/logger/configure.py
fastapi_ecommerce_ext/logger/middleware.py