Metadata-Version: 2.1
Name: fastapi-ecommerce-ext
Version: 0.3.3
Summary: logging extension for fastapi-microservices
Home-page: https://github.com/coolworld2049/fastapi-ecommerce/pypi/fastapi_ecommerce_ext
Download-URL: https://github.com/coolworld2049/fastapi-ecommerce/pypi/fastapi_ecommerce_ext-0.3.3.tar.gz
Author: coolworld2049
License: MIT
License-File: LICENSE.txt
